blenderforge/__init__.py
blenderforge/config.py
blenderforge/server.py
blenderforge/telemetry.py
blenderforge/telemetry_decorator.py
blenderforge-1.0.5.dist-info/licenses/LICENSE
blenderforge-1.0.5.dist-info/METADATA
blenderforge-1.0.5.dist-info/WHEEL
blenderforge-1.0.5.dist-info/entry_points.txt
blenderforge-1.0.5.dist-info/top_level.txt
blenderforge-1.0.5.dist-info/RECORD
