Metadata-Version: 2.4
Name: blenderforge
Version: 1.0.5
Summary: AI-powered Blender integration for 3D modeling and scene creation
Author-email: Mithun Gowda B <mithungowda.b7411@gmail.com>
Maintainer-email: Mithun Gowda B <mithungowda.b7411@gmail.com>
License: MIT
Project-URL: Homepage, https://github.com/mithun50/blenderforge
Project-URL: Documentation, https://github.com/mithun50/blenderforge#readme
Project-URL: Repository, https://github.com/mithun50/blenderforge.git
Project-URL: Issues, https://github.com/mithun50/blenderforge/issues
Keywords: blender,mcp,ai,3d,modeling,claude,llm
Classifier: Development Status :: 4 - Beta
Classifier: Intended Audience :: Developers
Classifier: License :: OSI Approved :: MIT License
Classifier: Operating System :: OS Independent
Classifier: Programming Language :: Python :: 3
Classifier: Programming Language :: Python :: 3.10
Classifier: Programming Language :: Python :: 3.11
Classifier: Programming Language :: Python :: 3.12
Classifier: Programming Language :: Python :: 3.13
Classifier: Topic :: Multimedia :: Graphics :: 3D Modeling
Classifier: Topic :: Scientific/Engineering :: Artificial Intelligence
Requires-Python: >=3.10
License-File: LICENSE
Requires-Dist: mcp[cli]>=1.3.0
Requires-Dist: supabase>=2.0.0
Requires-Dist: tomli>=2.0.0; python_version < "3.11"
Provides-Extra: dev
Requires-Dist: pytest>=7.0.0; extra == "dev"
Requires-Dist: pytest-cov>=4.0.0; extra == "dev"
Requires-Dist: pytest-asyncio>=0.21.0; extra == "dev"
Requires-Dist: ruff>=0.1.0; extra == "dev"
Requires-Dist: mypy>=1.0.0; extra == "dev"
Requires-Dist: pre-commit>=3.0.0; extra == "dev"
Dynamic: license-file
